bubop/__init__.py
bubop/arg_parser.py
bubop/classes.py
bubop/cli.py
bubop/common_dir.py
bubop/crypto.py
bubop/exceptions.py
bubop/exit_hooks.py
bubop/fs.py
bubop/inspect.py
bubop/logging.py
bubop/misc.py
bubop/prefs_manager.py
bubop/py.typed
bubop/serial.py
bubop/string.py
bubop/test.py
bubop/time.py
bubop-0.2.3.dist-info/LICENSE.md
bubop-0.2.3.dist-info/METADATA
bubop-0.2.3.dist-info/WHEEL
bubop-0.2.3.dist-info/RECORD
