Metadata-Version: 2.3
Name: bubop
Version: 0.2.3
Summary: Bergercookie's Useful Bits Of Python
License: MIT
Keywords: utilities,utils
Author: Nikos Koukis
Author-email: nickkouk@gmail.com
Requires-Python: >=3.10.0,<3.14
Classifier: Framework :: Pytest
Classifier: License :: OSI Approved :: MIT License
Classifier: Natural Language :: English
Classifier: Operating System :: Unix
Classifier: Programming Language :: Python
Classifier: Programming Language :: Python :: 3
Classifier: Programming Language :: Python :: 3.10
Classifier: Programming Language :: Python :: 3.11
Classifier: Programming Language :: Python :: 3.12
Classifier: Programming Language :: Python :: 3.13
Classifier: Programming Language :: Python :: 3 :: Only
Classifier: Topic :: Utilities
Provides-Extra: dev
Provides-Extra: docs
Requires-Dist: PyYAML (>=6.0.2,<6.1.0)
Requires-Dist: black (>=24.10.0,<25.0.0) ; extra == "dev"
Requires-Dist: check-jsonschema (>=0.31.3,<0.32.0) ; extra == "dev"
Requires-Dist: coverage (>=7.8.0,<8.0.0) ; extra == "dev"
Requires-Dist: coveralls (>=4.0.1,<5.0.0) ; (python_version < "3.13") and (extra == "dev")
Requires-Dist: identify (>=2.6.10,<3.0.0) ; extra == "dev"
Requires-Dist: isort (>=5.13.2,<6.0.0) ; extra == "dev"
Requires-Dist: loguru (>=0.7.3,<0.8.0)
Requires-Dist: mock (>=5.2.0,<6.0.0) ; extra == "dev"
Requires-Dist: mypy (>=1.15.0,<2.0.0) ; extra == "dev"
Requires-Dist: pdbp (>=1.7.0,<2.0.0) ; extra == "dev"
Requires-Dist: pre-commit (>=4.2.0,<5.0.0) ; extra == "dev"
Requires-Dist: pyfakefs (>=5.8.0,<6.0.0) ; extra == "dev"
Requires-Dist: pylint (>=3.3.7,<4.0.0) ; extra == "dev"
Requires-Dist: pyright (>=1.1.400,<2.0.0) ; extra == "dev"
Requires-Dist: pytest (>=8.3.5,<9.0.0) ; extra == "dev"
Requires-Dist: python-dateutil (>=2.9.0.post0,<3.0.0)
Requires-Dist: pyupgrade (>=3.19.1,<4.0.0) ; extra == "dev"
Requires-Dist: sphinx (>=8.1.3,<9.0.0) ; extra == "docs"
Requires-Dist: sphinx (>=8.2,<9.0) ; (python_version >= "3.11") and (extra == "docs")
Requires-Dist: sphinx-copybutton (>=0.5.2,<0.6.0) ; extra == "docs"
Requires-Dist: sphinx-rtd-theme (>=3.0.2,<4.0.0) ; extra == "docs"
Requires-Dist: sphinxcontrib-spelling (>=8.0.1,<9.0.0) ; extra == "docs"
Requires-Dist: tqdm (>=4.67.1,<5.0.0)
Requires-Dist: types-PyYAML (>=6.0.12.20250402,<7.0.0.0) ; extra == "dev"
Requires-Dist: types-python-dateutil (>=2.9.0.20241206,<3.0.0.0) ; extra == "dev"
Project-URL: Homepage, https://github.com/bergercookie/bubop
Project-URL: Repository, https://github.com/bergercookie/bubop
